README.md
setup.py
mlrose_reborn/__init__.py
mlrose_reborn.egg-info/PKG-INFO
mlrose_reborn.egg-info/SOURCES.txt
mlrose_reborn.egg-info/dependency_links.txt
mlrose_reborn.egg-info/not-zip-safe
mlrose_reborn.egg-info/requires.txt
mlrose_reborn.egg-info/top_level.txt
mlrose_reborn/algorithms/__init__.py
mlrose_reborn/algorithms/ga.py
mlrose_reborn/algorithms/gd.py
mlrose_reborn/algorithms/hc.py
mlrose_reborn/algorithms/mimic.py
mlrose_reborn/algorithms/rhc.py
mlrose_reborn/algorithms/sa.py
mlrose_reborn/algorithms/crossovers/__init__.py
mlrose_reborn/algorithms/crossovers/_crossover_base.py
mlrose_reborn/algorithms/crossovers/one_point_crossover.py
mlrose_reborn/algorithms/crossovers/tsp_crossover.py
mlrose_reborn/algorithms/crossovers/uniform_crossover.py
mlrose_reborn/algorithms/decay/__init__.py
mlrose_reborn/algorithms/decay/arith_decay.py
mlrose_reborn/algorithms/decay/custom_schedule.py
mlrose_reborn/algorithms/decay/exp_decay.py
mlrose_reborn/algorithms/decay/geom_decay.py
mlrose_reborn/algorithms/mutators/__init__.py
mlrose_reborn/algorithms/mutators/_mutator_base.py
mlrose_reborn/algorithms/mutators/change_one_mutator.py
mlrose_reborn/algorithms/mutators/discrete_mutator.py
mlrose_reborn/algorithms/mutators/shift_one_mutator.py
mlrose_reborn/algorithms/mutators/swap_mutator.py
mlrose_reborn/decorators/__init__.py
mlrose_reborn/decorators/short_name_decorator.py
mlrose_reborn/fitness/__init__.py
mlrose_reborn/fitness/_discrete_peaks_base.py
mlrose_reborn/fitness/continuous_peaks.py
mlrose_reborn/fitness/custom_fitness.py
mlrose_reborn/fitness/flip_flop.py
mlrose_reborn/fitness/four_peaks.py
mlrose_reborn/fitness/knapsack.py
mlrose_reborn/fitness/max_k_color.py
mlrose_reborn/fitness/one_max.py
mlrose_reborn/fitness/queens.py
mlrose_reborn/fitness/six_peaks.py
mlrose_reborn/fitness/travelling_sales.py
mlrose_reborn/generators/__init__.py
mlrose_reborn/generators/flip_flop_generator.py
mlrose_reborn/generators/knapsack_generator.py
mlrose_reborn/generators/max_k_color_generator.py
mlrose_reborn/generators/queens_generator.py
mlrose_reborn/generators/tsp_generator.py
mlrose_reborn/gridsearch/__init__.py
mlrose_reborn/gridsearch/grid_search_mixin.py
