Metadata-Version: 2.1
Name: mlrose-reborn
Version: 2.0.0
Summary: mlrose_reborn: Machine Learning, Randomized Optimization and Search
Home-page: https://github.com/ryanmcdermott/mlrose
Author: Genevieve Hayes (modifed by Andrew Rollings, forked by Ryan McDermott)
License: BSD
Platform: UNKNOWN
Classifier: Intended Audience :: Education
Classifier: Intended Audience :: Science/Research
Classifier: Natural Language :: English
Classifier: License :: OSI Approved :: BSD License
Classifier: Programming Language :: Python
Classifier: Programming Language :: Python :: 3
Classifier: Topic :: Scientific/Engineering
Classifier: Topic :: Scientific/Engineering :: Artificial Intelligence
Classifier: Topic :: Scientific/Engineering :: Mathematics
Classifier: Topic :: Software Development :: Libraries
Classifier: Topic :: Software Development :: Libraries :: Python Modules
Requires-Python: >=3
